LICENSE
MANIFEST.in
README.rst
VERSION
requirements.txt
setup.cfg
setup.py
ldeep/__init__.py
ldeep/__main__.py
ldeep.egg-info/PKG-INFO
ldeep.egg-info/SOURCES.txt
ldeep.egg-info/dependency_links.txt
ldeep.egg-info/entry_points.txt
ldeep.egg-info/requires.txt
ldeep.egg-info/top_level.txt
ldeep.egg-info/zip-safe
ldeep/utils/__init__.py
ldeep/utils/sddl.py
ldeep/utils/structure.py
ldeep/views/__init__.py
ldeep/views/activedirectory.py
ldeep/views/cache_activedirectory.py
ldeep/views/constants.py
ldeep/views/ldap_activedirectory.py
ldeep/views/structures.py