Metadata-Version: 2.1
Name: ldeep
Version: 1.0.33
Summary: In-depth ldap enumeration utility
Home-page: https://github.com/franc-pentest/ldeep
Author: b0z, flgy
Author-email: bastien@faure.io, florian.guilbert@synacktiv.com
License: MIT
Keywords: pentesting security windows active-directory networks
Platform: any
Classifier: Development Status :: 4 - Beta
Classifier: Intended Audience :: Information Technology
Classifier: License :: OSI Approved :: MIT License
Classifier: Programming Language :: Python
Classifier: Programming Language :: Python :: 3.3
Classifier: Programming Language :: Python :: 3 :: Only
Classifier: Topic :: Security
Classifier: Operating System :: OS Independent
Requires-Python: >=3.3
License-File: LICENSE
